aiverify_environment_corruptions/__init__.py
aiverify_environment_corruptions/__main__.py
aiverify_environment_corruptions/algo.meta.json
aiverify_environment_corruptions/algo.py
aiverify_environment_corruptions/algo_init.py
aiverify_environment_corruptions/input.schema.json
aiverify_environment_corruptions/output.schema.json
aiverify_environment_corruptions/plugin_init.py
aiverify_environment_corruptions/utils/__init__.py
aiverify_environment_corruptions/utils/environment.py
aiverify_environment_corruptions-2.1.0.dist-info/METADATA
aiverify_environment_corruptions-2.1.0.dist-info/WHEEL
aiverify_environment_corruptions-2.1.0.dist-info/entry_points.txt
aiverify_environment_corruptions-2.1.0.dist-info/licenses/AUTHORS.rst
aiverify_environment_corruptions-2.1.0.dist-info/licenses/LICENSE
aiverify_environment_corruptions-2.1.0.dist-info/licenses/NOTICE.md
aiverify_environment_corruptions-2.1.0.dist-info/RECORD
