Metadata-Version: 2.4
Name: aiverify-environment-corruptions
Version: 2.1.0
Summary: Part of AI Verify image corruption toolbox. This package includes algorithms that add environmental corruptions (rain, fog and snow) to images at different severity levels, to test the robustness of machine learning models.
Author: AI Verify
License-File: AUTHORS.rst
License-File: LICENSE
License-File: NOTICE.md
Requires-Python: <3.13,>=3.10
Requires-Dist: aiverify-test-engine[all]>=2.1.0
Requires-Dist: albumentations>=2.0.4
Requires-Dist: numpy==1.26.4
Requires-Dist: pandas==2.2.2
Requires-Dist: pillow==10.4.0
